EMITL2ARFL/EMITL2ARFL.py
EMITL2ARFL/__init__.py
EMITL2ARFL/apply_geometry_lookup_table.py
EMITL2ARFL/constants.py
EMITL2ARFL/emit_ortho_raster.py
EMITL2ARFL/emit_xarray.py
EMITL2ARFL/extract_GLT.py
EMITL2ARFL/generate_earthaccess_query.py
EMITL2ARFL/get_pixel_center_coords.py
EMITL2ARFL/granule.py
EMITL2ARFL/ortho_xr.py
EMITL2ARFL/retrieve_EMIT_L2A_RFL_granule.py
EMITL2ARFL/search_EMIT_L2A_RFL_granules.py
EMITL2ARFL/search_earthaccess_granules.py
EMITL2ARFL/spatially_constrain_earthaccess_query.py
EMITL2ARFL/temporally_constrain_earthaccess_query.py
EMITL2ARFL/version.py
EMITL2ARFL/version.txt
emitl2arfl-1.0.1.dist-info/licenses/LICENSE
emitl2arfl-1.0.1.dist-info/METADATA
emitl2arfl-1.0.1.dist-info/WHEEL
emitl2arfl-1.0.1.dist-info/top_level.txt
emitl2arfl-1.0.1.dist-info/RECORD
