Metadata-Version: 2.4
Name: EMITL2ARFL
Version: 1.0.1
Summary: EMIT L2A Estimated Surface Reflectance and Uncertainty and Masks 60 m Search and Download Utility
Author-email: "Gregory H. Halverson" <gregory.h.halverson@jpl.nasa.gov>
Project-URL: Homepage, https://github.com/STARS-Data-Fusion/EMITL2ARFL
Classifier: Programming Language :: Python :: 3
Classifier: Operating System :: OS Independent
Requires-Python: >=3.10
License-File: LICENSE
Requires-Dist: colored-logging
Requires-Dist: earthaccess
Requires-Dist: geopandas
Requires-Dist: netCDF4
Requires-Dist: python-dateutil
Requires-Dist: rasters
Requires-Dist: rioxarray
Requires-Dist: spectral
Requires-Dist: xarray
Provides-Extra: dev
Requires-Dist: build; extra == "dev"
Requires-Dist: pytest>=6.0; extra == "dev"
Requires-Dist: pytest-cov; extra == "dev"
Requires-Dist: jupyter; extra == "dev"
Requires-Dist: pytest; extra == "dev"
Requires-Dist: twine; extra == "dev"
Dynamic: license-file
